{
  "updatedAt": "2026-06-24T19:00:00+09:00",
  "session": "PM",
  "note": "한국=6/24(수) '검은 화요일(-9.99%)' 딛고 반등 마감: 코스피 +3.26%(8,471.02), 코스닥 +1.99%(909.30). 삼성전자 +9%대 시총 1위 탈환(90조 자사주 기대), SK하이닉스는 약세(7/10 美 ADR 45조 조달). 단 환율 1,541.8원 종가(금융위기 후 최고)·외국인 순매도·MSCI 선진 편입 12수 불발은 부담. 미국=6/23밤 반도체 투매 지속(마이크론 -13%)·매파 워시 연준(도이체방크 '연내 2회 인상' 전망). 호르무즈 긴장완화로 유가는 안정. 관전=국민연금 리밸런싱 유예 만료(1주 앞·최대 60조)·빚투 반대매매.",
  "stock_fng": { "value": 30, "label": "Fear", "source": "https://www.cnn.com/markets/fear-and-greed" },
  "indices": [
    { "name": "코스피", "value": "8,471.02", "change": "+3.26% (+267.18p, 반등 마감)", "source": "https://view.asiae.co.kr/article/2026062415354832710" },
    { "name": "코스닥", "value": "909.30", "change": "+1.99% (+17.78p)", "source": "https://view.asiae.co.kr/article/2026062415360538481" },
    { "name": "코스피200 변동성지수(VKOSPI)", "value": "금융위기 이후 최고", "change": "공포 극대 지속", "source": "https://www.yna.co.kr/view/AKR20260624047051008" },
    { "name": "나스닥", "value": "반도체 투매 지속(6/23밤)", "change": "마이크론 -13% 등 AI 거품 점검", "source": "https://www.hankyung.com/article/2026062440596" },
    { "name": "美 6월 제조업 PMI", "value": "55.7", "change": "예상밖 깜짝 확장", "source": "https://www.hankyung.com/article/202606233909i" },
    { "name": "국제유가(WTI)", "value": "4개월 최저권", "change": "↓ 호르무즈 긴장완화(경유가 2천원선 아래)", "source": "https://www.yna.co.kr/view/AKR20260624144900003" },
    { "name": "원/달러", "value": "1,541.8", "change": "+2.7 (15:30 종가·금융위기 후 최고)", "source": "https://www.yna.co.kr/view/AKR20260624128100002" }
  ]
}
