{
 "updatedAt": "2026-07-09T09:30:51+09:00",
 "companies": {
  "이지트로닉스(377330)": {
   "market": "韓",
   "type": "leading",
   "firstSeen": "2026-07-07",
   "firstPrice": 2280,
   "lastPrice": 2230,
   "changePct": -2.19,
   "points": 2,
   "series": {
    "2026-07-07": 2280,
    "2026-07-08": 2230
   }
  },
  "비에이치아이(083650)": {
   "market": "韓",
   "type": "leading",
   "firstSeen": "2026-07-07",
   "firstPrice": 49600,
   "lastPrice": 45850,
   "changePct": -7.56,
   "points": 2,
   "series": {
    "2026-07-07": 49600,
    "2026-07-08": 45850
   }
  },
  "대동(000490)": {
   "market": "韓",
   "type": "leading",
   "firstSeen": "2026-07-07",
   "firstPrice": 7230,
   "lastPrice": 7040,
   "changePct": -2.63,
   "points": 2,
   "series": {
    "2026-07-07": 7230,
    "2026-07-08": 7040
   }
  },
  "퓨쳐켐(220100)": {
   "market": "韓",
   "type": "leading",
   "firstSeen": "2026-07-07",
   "firstPrice": 9190,
   "lastPrice": 8850,
   "changePct": -3.7,
   "points": 2,
   "series": {
    "2026-07-07": 9190,
    "2026-07-08": 8850
   }
  },
  "태성(323280)": {
   "market": "韓",
   "type": "leading",
   "firstSeen": "2026-07-07",
   "firstPrice": 38350,
   "lastPrice": 35950,
   "changePct": -6.26,
   "points": 2,
   "series": {
    "2026-07-07": 38350,
    "2026-07-08": 35950
   }
  },
  "옵트론텍(082210)": {
   "market": "韓",
   "type": "leading",
   "firstSeen": "2026-07-07",
   "firstPrice": 1654,
   "lastPrice": 1605,
   "changePct": -2.96,
   "points": 2,
   "series": {
    "2026-07-07": 1654,
    "2026-07-08": 1605
   }
  },
  "씨싸이트(109670)": {
   "market": "韓",
   "type": "leading",
   "firstSeen": "2026-07-07",
   "firstPrice": 4340,
   "lastPrice": 4055,
   "changePct": -6.57,
   "points": 2,
   "series": {
    "2026-07-07": 4340,
    "2026-07-08": 4055
   }
  },
  "에이비온(203400)": {
   "market": "韓",
   "type": "leading",
   "firstSeen": "2026-07-07",
   "firstPrice": 775,
   "lastPrice": 683,
   "changePct": -11.87,
   "points": 2,
   "series": {
    "2026-07-07": 775,
    "2026-07-08": 683
   }
  },
  "오텍캐리어(126560)": {
   "market": "韓",
   "type": "leading",
   "firstSeen": "2026-07-07",
   "firstPrice": 2995,
   "lastPrice": 2980,
   "changePct": -0.5,
   "points": 2,
   "series": {
    "2026-07-07": 2995,
    "2026-07-08": 2980
   }
  },
  "파라텍(033540)": {
   "market": "韓",
   "type": "leading",
   "firstSeen": "2026-07-07",
   "firstPrice": 953,
   "lastPrice": 931,
   "changePct": -2.31,
   "points": 2,
   "series": {
    "2026-07-07": 953,
    "2026-07-08": 931
   }
  },
  "쎄크(081180)": {
   "market": "韓",
   "type": "discovery",
   "firstSeen": "2026-07-07",
   "firstPrice": 5670,
   "lastPrice": 5600,
   "changePct": -1.23,
   "points": 2,
   "series": {
    "2026-07-07": 5670,
    "2026-07-08": 5600
   }
  },
  "케이엠제약(225430)": {
   "market": "韓",
   "type": "discovery",
   "firstSeen": "2026-07-07",
   "firstPrice": 1589,
   "lastPrice": 1421,
   "changePct": -10.57,
   "points": 2,
   "series": {
    "2026-07-07": 1589,
    "2026-07-08": 1421
   }
  },
  "다이나믹솔루션(290660)": {
   "market": "韓",
   "type": "leading",
   "firstSeen": "2026-06-21",
   "firstPrice": 939,
   "lastPrice": 1442,
   "changePct": 53.57,
   "points": 5,
   "series": {
    "2026-06-21": 939,
    "2026-06-24": 939,
    "2026-06-30": 1983,
    "2026-07-07": 1578,
    "2026-07-08": 1442
   }
  },
  "에스피지(058610)": {
   "market": "韓",
   "type": "leading",
   "firstSeen": "2026-06-21",
   "firstPrice": 86400,
   "lastPrice": 67800,
   "changePct": -21.53,
   "points": 5,
   "series": {
    "2026-06-21": 86400,
    "2026-06-24": 80200,
    "2026-06-30": 80300,
    "2026-07-07": 71600,
    "2026-07-08": 67800
   }
  },
  "와이엠티(251370)": {
   "market": "韓",
   "type": "leading",
   "firstSeen": "2026-06-22",
   "firstPrice": 12980,
   "lastPrice": 9240,
   "changePct": -28.81,
   "points": 5,
   "series": {
    "2026-06-22": 12980,
    "2026-06-25": 10940,
    "2026-07-01": 11270,
    "2026-07-07": 9450,
    "2026-07-08": 9240
   }
  },
  "필옵틱스(161580)": {
   "market": "韓",
   "type": "leading",
   "firstSeen": "2026-06-22",
   "firstPrice": 41250,
   "lastPrice": 29800,
   "changePct": -27.76,
   "points": 5,
   "series": {
    "2026-06-22": 41250,
    "2026-06-25": 37300,
    "2026-07-01": 36550,
    "2026-07-07": 31850,
    "2026-07-08": 29800
   }
  },
  "엠케이전자(033160)": {
   "market": "韓",
   "type": "leading",
   "firstSeen": "2026-06-22",
   "firstPrice": 27150,
   "lastPrice": 14740,
   "changePct": -45.71,
   "points": 5,
   "series": {
    "2026-06-22": 27150,
    "2026-06-25": 22000,
    "2026-07-01": 18380,
    "2026-07-07": 14440,
    "2026-07-08": 14740
   }
  },
  "나노팀(417010)": {
   "market": "韓",
   "type": "leading",
   "firstSeen": "2026-06-22",
   "firstPrice": 6220,
   "lastPrice": 4790,
   "changePct": -22.99,
   "points": 5,
   "series": {
    "2026-06-22": 6220,
    "2026-06-25": 5190,
    "2026-07-01": 5580,
    "2026-07-07": 4895,
    "2026-07-08": 4790
   }
  },
  "에스에너지(095910)": {
   "market": "韓",
   "type": "leading",
   "firstSeen": "2026-06-22",
   "firstPrice": 1126,
   "lastPrice": 791,
   "changePct": -29.75,
   "points": 5,
   "series": {
    "2026-06-22": 1126,
    "2026-06-25": 1015,
    "2026-07-01": 878,
    "2026-07-07": 810,
    "2026-07-08": 791
   }
  },
  "비츠로셀(082920)": {
   "market": "韓",
   "type": "leading",
   "firstSeen": "2026-06-23",
   "firstPrice": 40950,
   "lastPrice": 32150,
   "changePct": -21.49,
   "points": 5,
   "series": {
    "2026-06-23": 40950,
    "2026-06-26": 36950,
    "2026-07-02": 36850,
    "2026-07-07": 34600,
    "2026-07-08": 32150
   }
  },
  "마이크로디지탈(305090)": {
   "market": "韓",
   "type": "leading",
   "firstSeen": "2026-06-23",
   "firstPrice": 2245,
   "lastPrice": 2090,
   "changePct": -6.9,
   "points": 5,
   "series": {
    "2026-06-23": 2245,
    "2026-06-26": 2090,
    "2026-07-02": 2075,
    "2026-07-07": 2145,
    "2026-07-08": 2090
   }
  },
  "네온테크(306620)": {
   "market": "韓",
   "type": "leading",
   "firstSeen": "2026-06-23",
   "firstPrice": 2710,
   "lastPrice": 1983,
   "changePct": -26.83,
   "points": 4,
   "series": {
    "2026-06-23": 2710,
    "2026-06-26": 2540,
    "2026-07-02": 2290,
    "2026-07-08": 1983
   }
  },
  "이엠앤아이(083470)": {
   "market": "韓",
   "type": "leading",
   "firstSeen": "2026-06-23",
   "firstPrice": 877,
   "lastPrice": 799,
   "changePct": -8.89,
   "points": 5,
   "series": {
    "2026-06-23": 877,
    "2026-06-26": 909,
    "2026-07-02": 842,
    "2026-07-07": 840,
    "2026-07-08": 799
   }
  },
  "위지트(036090)": {
   "market": "韓",
   "type": "leading",
   "firstSeen": "2026-06-23",
   "firstPrice": 1742,
   "lastPrice": 1310,
   "changePct": -24.8,
   "points": 5,
   "series": {
    "2026-06-23": 1742,
    "2026-06-26": 1603,
    "2026-07-02": 1410,
    "2026-07-07": 1357,
    "2026-07-08": 1310
   }
  },
  "라온시큐어(042510)": {
   "market": "韓",
   "type": "leading",
   "firstSeen": "2026-06-24",
   "firstPrice": 7260,
   "lastPrice": 7390,
   "changePct": 1.79,
   "points": 5,
   "series": {
    "2026-06-24": 7260,
    "2026-06-29": 7450,
    "2026-07-03": 7300,
    "2026-07-07": 7210,
    "2026-07-08": 7390
   }
  },
  "캐프(198080)": {
   "market": "韓",
   "type": "leading",
   "firstSeen": "2026-06-25",
   "firstPrice": 2105,
   "lastPrice": 2150,
   "changePct": 2.14,
   "points": 5,
   "series": {
    "2026-06-25": 2105,
    "2026-06-30": 2225,
    "2026-07-06": 2200,
    "2026-07-07": 2165,
    "2026-07-08": 2150
   }
  },
  "티로보틱스(117730)": {
   "market": "韓",
   "type": "leading",
   "firstSeen": "2026-06-26",
   "firstPrice": 12230,
   "lastPrice": 11930,
   "changePct": -2.45,
   "points": 4,
   "series": {
    "2026-06-26": 12230,
    "2026-07-01": 14600,
    "2026-07-07": 12420,
    "2026-07-08": 11930
   }
  },
  "코이즈(121850)": {
   "market": "韓",
   "type": "leading",
   "firstSeen": "2026-06-26",
   "firstPrice": 1251,
   "lastPrice": 1418,
   "changePct": 13.35,
   "points": 4,
   "series": {
    "2026-06-26": 1251,
    "2026-07-01": 1447,
    "2026-07-07": 1490,
    "2026-07-08": 1418
   }
  },
  "멕아이씨에스(058110)": {
   "market": "韓",
   "type": "leading",
   "firstSeen": "2026-06-26",
   "firstPrice": 2005,
   "lastPrice": 1860,
   "changePct": -7.23,
   "points": 4,
   "series": {
    "2026-06-26": 2005,
    "2026-07-01": 1961,
    "2026-07-07": 1870,
    "2026-07-08": 1860
   }
  },
  "에어레인(163280)": {
   "market": "韓",
   "type": "leading",
   "firstSeen": "2026-06-27",
   "firstPrice": 3840,
   "lastPrice": 3535,
   "changePct": -7.94,
   "points": 4,
   "series": {
    "2026-06-27": 3840,
    "2026-07-01": 3985,
    "2026-07-07": 3655,
    "2026-07-08": 3535
   }
  },
  "에이루트(096690)": {
   "market": "韓",
   "type": "leading",
   "firstSeen": "2026-06-30",
   "firstPrice": 5060,
   "lastPrice": 5380,
   "changePct": 6.32,
   "points": 4,
   "series": {
    "2026-06-30": 5060,
    "2026-07-03": 5180,
    "2026-07-07": 5390,
    "2026-07-08": 5380
   }
  },
  "씨앤지하이테크(264660)": {
   "market": "韓",
   "type": "leading",
   "firstSeen": "2026-06-30",
   "firstPrice": 13420,
   "lastPrice": 12290,
   "changePct": -8.42,
   "points": 4,
   "series": {
    "2026-06-30": 13420,
    "2026-07-03": 13180,
    "2026-07-07": 12490,
    "2026-07-08": 12290
   }
  },
  "코아시아씨엠(196450)": {
   "market": "韓",
   "type": "leading",
   "firstSeen": "2026-06-30",
   "firstPrice": 817,
   "lastPrice": 945,
   "changePct": 15.67,
   "points": 4,
   "series": {
    "2026-06-30": 817,
    "2026-07-03": 944,
    "2026-07-07": 990,
    "2026-07-08": 945
   }
  },
  "케이엔에스(432470)": {
   "market": "韓",
   "type": "leading",
   "firstSeen": "2026-07-01",
   "firstPrice": 8050,
   "lastPrice": 7150,
   "changePct": -11.18,
   "points": 4,
   "series": {
    "2026-07-01": 8050,
    "2026-07-06": 7640,
    "2026-07-07": 7400,
    "2026-07-08": 7150
   }
  },
  "오텍(067170)": {
   "market": "韓",
   "type": "leading",
   "firstSeen": "2026-07-01",
   "firstPrice": 2895,
   "lastPrice": 2720,
   "changePct": -6.04,
   "points": 4,
   "series": {
    "2026-07-01": 2895,
    "2026-07-06": 2705,
    "2026-07-07": 2900,
    "2026-07-08": 2720
   }
  },
  "유아이디(069330)": {
   "market": "韓",
   "type": "leading",
   "firstSeen": "2026-07-01",
   "firstPrice": 1070,
   "lastPrice": 972,
   "changePct": -9.16,
   "points": 4,
   "series": {
    "2026-07-01": 1070,
    "2026-07-06": 979,
    "2026-07-07": 1004,
    "2026-07-08": 972
   }
  },
  "대동금속(020400)": {
   "market": "韓",
   "type": "leading",
   "firstSeen": "2026-07-02",
   "firstPrice": 3425,
   "lastPrice": 3120,
   "changePct": -8.91,
   "points": 3,
   "series": {
    "2026-07-02": 3425,
    "2026-07-07": 3150,
    "2026-07-08": 3120
   }
  },
  "뉴보텍(060260)": {
   "market": "韓",
   "type": "leading",
   "firstSeen": "2026-07-02",
   "firstPrice": 1671,
   "lastPrice": 1494,
   "changePct": -10.59,
   "points": 3,
   "series": {
    "2026-07-02": 1671,
    "2026-07-07": 1569,
    "2026-07-08": 1494
   }
  },
  "솔루스첨단소재(336370)": {
   "market": "韓",
   "type": "leading",
   "firstSeen": "2026-07-03",
   "firstPrice": 8250,
   "lastPrice": 7500,
   "changePct": -9.09,
   "points": 3,
   "series": {
    "2026-07-03": 8250,
    "2026-07-07": 7900,
    "2026-07-08": 7500
   }
  },
  "글로벌에스엠(900070)": {
   "market": "韓",
   "type": "leading",
   "firstSeen": "2026-07-03",
   "firstPrice": 1006,
   "lastPrice": 1046,
   "changePct": 3.98,
   "points": 3,
   "series": {
    "2026-07-03": 1006,
    "2026-07-07": 1070,
    "2026-07-08": 1046
   }
  },
  "하나기술(299030)": {
   "market": "韓",
   "type": "leading",
   "firstSeen": "2026-07-03",
   "firstPrice": 13580,
   "lastPrice": 12200,
   "changePct": -10.16,
   "points": 3,
   "series": {
    "2026-07-03": 13580,
    "2026-07-07": 12990,
    "2026-07-08": 12200
   }
  },
  "이수스페셜티케미컬(457190)": {
   "market": "韓",
   "type": "leading",
   "firstSeen": "2026-07-03",
   "firstPrice": 68200,
   "lastPrice": 60200,
   "changePct": -11.73,
   "points": 3,
   "series": {
    "2026-07-03": 68200,
    "2026-07-07": 65000,
    "2026-07-08": 60200
   }
  },
  "대한전선(001440)": {
   "market": "韓",
   "type": "leading",
   "firstSeen": "2026-07-03",
   "firstPrice": 32900,
   "lastPrice": 28200,
   "changePct": -14.29,
   "points": 3,
   "series": {
    "2026-07-03": 32900,
    "2026-07-07": 30550,
    "2026-07-08": 28200
   }
  },
  "일진전기(103590)": {
   "market": "韓",
   "type": "leading",
   "firstSeen": "2026-07-03",
   "firstPrice": 75300,
   "lastPrice": 62800,
   "changePct": -16.6,
   "points": 3,
   "series": {
    "2026-07-03": 75300,
    "2026-07-07": 68100,
    "2026-07-08": 62800
   }
  },
  "한국주강(025890)": {
   "market": "韓",
   "type": "leading",
   "firstSeen": "2026-07-04",
   "firstPrice": 2255,
   "lastPrice": 2210,
   "changePct": -2.0,
   "points": 3,
   "series": {
    "2026-07-04": 2255,
    "2026-07-07": 2235,
    "2026-07-08": 2210
   }
  },
  "와이씨켐(112290)": {
   "market": "韓",
   "type": "leading",
   "firstSeen": "2026-07-04",
   "firstPrice": 10320,
   "lastPrice": 9100,
   "changePct": -11.82,
   "points": 3,
   "series": {
    "2026-07-04": 10320,
    "2026-07-07": 9910,
    "2026-07-08": 9100
   }
  },
  "디케이락(105740)": {
   "market": "韓",
   "type": "leading",
   "firstSeen": "2026-07-04",
   "firstPrice": 6860,
   "lastPrice": 6470,
   "changePct": -5.69,
   "points": 3,
   "series": {
    "2026-07-04": 6860,
    "2026-07-07": 6700,
    "2026-07-08": 6470
   }
  },
  "한국피아이엠(448900)": {
   "market": "韓",
   "type": "leading",
   "firstSeen": "2026-07-04",
   "firstPrice": 53600,
   "lastPrice": 45350,
   "changePct": -15.39,
   "points": 3,
   "series": {
    "2026-07-04": 53600,
    "2026-07-07": 50200,
    "2026-07-08": 45350
   }
  },
  "성호전자(043260)": {
   "market": "韓",
   "type": "discovery",
   "firstSeen": "2026-07-06",
   "firstPrice": 21250,
   "lastPrice": 18550,
   "changePct": -12.71,
   "points": 3,
   "series": {
    "2026-07-06": 21250,
    "2026-07-07": 19400,
    "2026-07-08": 18550
   }
  },
  "케이엔솔(053080)": {
   "market": "韓",
   "type": "discovery",
   "firstSeen": "2026-07-06",
   "firstPrice": 9350,
   "lastPrice": 8820,
   "changePct": -5.67,
   "points": 3,
   "series": {
    "2026-07-06": 9350,
    "2026-07-07": 8960,
    "2026-07-08": 8820
   }
  },
  "나우로보틱스(459510)": {
   "market": "韓",
   "type": "discovery",
   "firstSeen": "2026-07-01",
   "firstPrice": 15230,
   "lastPrice": 13000,
   "changePct": -14.64,
   "points": 4,
   "series": {
    "2026-07-01": 15230,
    "2026-07-06": 13890,
    "2026-07-07": 13220,
    "2026-07-08": 13000
   }
  },
  "케이지에이(455180)": {
   "market": "韓",
   "type": "discovery",
   "firstSeen": "2026-07-07",
   "firstPrice": 1315,
   "lastPrice": 1297,
   "changePct": -1.37,
   "points": 2,
   "series": {
    "2026-07-07": 1315,
    "2026-07-08": 1297
   }
  },
  "디알젬(263690)": {
   "market": "韓",
   "type": "leading",
   "firstSeen": "2026-07-07",
   "firstPrice": 5010,
   "lastPrice": 4965,
   "changePct": -0.9,
   "points": 2,
   "series": {
    "2026-07-07": 5010,
    "2026-07-08": 4965
   }
  },
  "엠젠솔루션(032790)": {
   "market": "韓",
   "type": "leading",
   "firstSeen": "2026-07-07",
   "firstPrice": 1090,
   "lastPrice": 1029,
   "changePct": -5.6,
   "points": 2,
   "series": {
    "2026-07-07": 1090,
    "2026-07-08": 1029
   }
  },
  "KH바텍(060720)": {
   "market": "韓",
   "type": "discovery",
   "firstSeen": "2026-06-21",
   "firstPrice": 11050,
   "lastPrice": 9960,
   "changePct": -9.86,
   "points": 5,
   "series": {
    "2026-06-21": 11050,
    "2026-06-24": 10640,
    "2026-06-30": 10750,
    "2026-07-07": 9960,
    "2026-07-08": 9960
   }
  },
  "삼화콘덴서(001820)": {
   "market": "韓",
   "type": "discovery",
   "firstSeen": "2026-06-21",
   "firstPrice": 167000,
   "lastPrice": 104300,
   "changePct": -37.54,
   "points": 5,
   "series": {
    "2026-06-21": 167000,
    "2026-06-24": 136000,
    "2026-06-30": 151000,
    "2026-07-07": 107800,
    "2026-07-08": 104300
   }
  },
  "씨에스윈드(112610)": {
   "market": "韓",
   "type": "discovery",
   "firstSeen": "2026-06-22",
   "firstPrice": 43450,
   "lastPrice": 40000,
   "changePct": -7.94,
   "points": 5,
   "series": {
    "2026-06-22": 43450,
    "2026-06-25": 41700,
    "2026-07-01": 45400,
    "2026-07-07": 41050,
    "2026-07-08": 40000
   }
  },
  "와이솔(122990)": {
   "market": "韓",
   "type": "discovery",
   "firstSeen": "2026-06-23",
   "firstPrice": 6700,
   "lastPrice": 6060,
   "changePct": -9.55,
   "points": 5,
   "series": {
    "2026-06-23": 6700,
    "2026-06-26": 6150,
    "2026-07-02": 6260,
    "2026-07-07": 6100,
    "2026-07-08": 6060
   }
  },
  "클로봇(466100)": {
   "market": "韓",
   "type": "discovery",
   "firstSeen": "2026-06-23",
   "firstPrice": 30400,
   "lastPrice": 25300,
   "changePct": -16.78,
   "points": 5,
   "series": {
    "2026-06-23": 30400,
    "2026-06-26": 28650,
    "2026-07-02": 28900,
    "2026-07-07": 26400,
    "2026-07-08": 25300
   }
  },
  "삼기(122350)": {
   "market": "韓",
   "type": "discovery",
   "firstSeen": "2026-06-24",
   "firstPrice": 1086,
   "lastPrice": 1906,
   "changePct": 75.51,
   "points": 5,
   "series": {
    "2026-06-24": 1086,
    "2026-06-29": 1907,
    "2026-07-03": 1801,
    "2026-07-07": 1898,
    "2026-07-08": 1906
   }
  },
  "씨메스로보틱스(475400)": {
   "market": "韓",
   "type": "discovery",
   "firstSeen": "2026-06-26",
   "firstPrice": 18440,
   "lastPrice": 16030,
   "changePct": -13.07,
   "points": 4,
   "series": {
    "2026-06-26": 18440,
    "2026-07-01": 19830,
    "2026-07-07": 16840,
    "2026-07-08": 16030
   }
  },
  "가온칩스(399720)": {
   "market": "韓",
   "type": "discovery",
   "firstSeen": "2026-06-26",
   "firstPrice": 37050,
   "lastPrice": 42800,
   "changePct": 15.52,
   "points": 4,
   "series": {
    "2026-06-26": 37050,
    "2026-07-01": 41050,
    "2026-07-07": 48950,
    "2026-07-08": 42800
   }
  },
  "칩스앤미디어(094360)": {
   "market": "韓",
   "type": "discovery",
   "firstSeen": "2026-06-26",
   "firstPrice": 11220,
   "lastPrice": 11190,
   "changePct": -0.27,
   "points": 4,
   "series": {
    "2026-06-26": 11220,
    "2026-07-01": 12160,
    "2026-07-07": 12180,
    "2026-07-08": 11190
   }
  },
  "케이쓰리아이(431190)": {
   "market": "韓",
   "type": "discovery",
   "firstSeen": "2026-06-30",
   "firstPrice": 2205,
   "lastPrice": 2250,
   "changePct": 2.04,
   "points": 4,
   "series": {
    "2026-06-30": 2205,
    "2026-07-03": 2440,
    "2026-07-07": 2410,
    "2026-07-08": 2250
   }
  },
  "미래산업(025560)": {
   "market": "韓",
   "type": "discovery",
   "firstSeen": "2026-06-30",
   "firstPrice": 60300,
   "lastPrice": 41750,
   "changePct": -30.76,
   "points": 4,
   "series": {
    "2026-06-30": 60300,
    "2026-07-03": 45700,
    "2026-07-07": 41750,
    "2026-07-08": 41750
   }
  },
  "유니슨(018000)": {
   "market": "韓",
   "type": "discovery",
   "firstSeen": "2026-07-01",
   "firstPrice": 1062,
   "lastPrice": 853,
   "changePct": -19.68,
   "points": 4,
   "series": {
    "2026-07-01": 1062,
    "2026-07-06": 925,
    "2026-07-07": 900,
    "2026-07-08": 853
   }
  },
  "삼현(437730)": {
   "market": "韓",
   "type": "discovery",
   "firstSeen": "2026-07-02",
   "firstPrice": 35100,
   "lastPrice": 30200,
   "changePct": -13.96,
   "points": 3,
   "series": {
    "2026-07-02": 35100,
    "2026-07-07": 33200,
    "2026-07-08": 30200
   }
  },
  "HB테크놀러지(078150)": {
   "market": "韓",
   "type": "discovery",
   "firstSeen": "2026-07-04",
   "firstPrice": 2100,
   "lastPrice": 1910,
   "changePct": -9.05,
   "points": 3,
   "series": {
    "2026-07-04": 2100,
    "2026-07-07": 1998,
    "2026-07-08": 1910
   }
  },
  "한농화성(011500)": {
   "market": "韓",
   "type": "discovery",
   "firstSeen": "2026-07-04",
   "firstPrice": 13310,
   "lastPrice": 11960,
   "changePct": -10.14,
   "points": 3,
   "series": {
    "2026-07-04": 13310,
    "2026-07-07": 12800,
    "2026-07-08": 11960
   }
  },
  "플래티어(367000)": {
   "market": "韓",
   "type": "discovery",
   "firstSeen": "2026-07-05",
   "firstPrice": 2935,
   "lastPrice": 2980,
   "changePct": 1.53,
   "points": 3,
   "series": {
    "2026-07-05": 2935,
    "2026-07-07": 2875,
    "2026-07-08": 2980
   }
  },
  "세명전기(017510)": {
   "market": "韓",
   "type": "discovery",
   "firstSeen": "2026-07-05",
   "firstPrice": 7710,
   "lastPrice": 6800,
   "changePct": -11.8,
   "points": 3,
   "series": {
    "2026-07-05": 7710,
    "2026-07-07": 7350,
    "2026-07-08": 6800
   }
  },
  "레이크머티리얼즈(281740)": {
   "market": "韓",
   "type": "discovery",
   "firstSeen": "2026-07-05",
   "firstPrice": 13110,
   "lastPrice": 12100,
   "changePct": -7.7,
   "points": 3,
   "series": {
    "2026-07-05": 13110,
    "2026-07-07": 12900,
    "2026-07-08": 12100
   }
  },
  "브이엠(089970)": {
   "market": "韓",
   "type": "discovery",
   "firstSeen": "2026-07-07",
   "firstPrice": 87200,
   "lastPrice": 85000,
   "changePct": -2.52,
   "points": 2,
   "series": {
    "2026-07-07": 87200,
    "2026-07-08": 85000
   }
  },
  "에이직랜드(445090)": {
   "market": "韓",
   "type": "leading",
   "firstSeen": "2026-07-08",
   "firstPrice": 17300,
   "lastPrice": 17300,
   "changePct": 0.0,
   "points": 1,
   "series": {
    "2026-07-08": 17300
   }
  },
  "이엠앤아이(481070)": {
   "market": "韓",
   "type": "leading",
   "firstSeen": "2026-07-08",
   "firstPrice": 15070,
   "lastPrice": 15070,
   "changePct": 0.0,
   "points": 1,
   "series": {
    "2026-07-08": 15070
   }
  },
  "SG(255220)": {
   "market": "韓",
   "type": "discovery",
   "firstSeen": "2026-07-08",
   "firstPrice": 1489,
   "lastPrice": 1489,
   "changePct": 0.0,
   "points": 1,
   "series": {
    "2026-07-08": 1489
   }
  },
  "스마트레이더시스템(424960)": {
   "market": "韓",
   "type": "discovery",
   "firstSeen": "2026-07-08",
   "firstPrice": 3620,
   "lastPrice": 3620,
   "changePct": 0.0,
   "points": 1,
   "series": {
    "2026-07-08": 3620
   }
  },
  "데이타솔루션(263800)": {
   "market": "韓",
   "type": "warning",
   "firstSeen": "2026-07-08",
   "firstPrice": 5940,
   "lastPrice": 5940,
   "changePct": 0.0,
   "points": 1,
   "series": {
    "2026-07-08": 5940
   }
  },
  "씨이랩(189330)": {
   "market": "韓",
   "type": "warning",
   "firstSeen": "2026-07-08",
   "firstPrice": 12620,
   "lastPrice": 12620,
   "changePct": 0.0,
   "points": 1,
   "series": {
    "2026-07-08": 12620
   }
  },
  "아이씨티케이(456010)": {
   "market": "韓",
   "type": "discovery",
   "firstSeen": "2026-07-08",
   "firstPrice": 14620,
   "lastPrice": 14620,
   "changePct": 0.0,
   "points": 1,
   "series": {
    "2026-07-08": 14620
   }
  },
  "케이사인(192250)": {
   "market": "韓",
   "type": "discovery",
   "firstSeen": "2026-07-08",
   "firstPrice": 7140,
   "lastPrice": 7140,
   "changePct": 0.0,
   "points": 1,
   "series": {
    "2026-07-08": 7140
   }
  },
  "에스투더블유(377480)": {
   "market": "韓",
   "type": "warning",
   "firstSeen": "2026-07-08",
   "firstPrice": 8490,
   "lastPrice": 8490,
   "changePct": 0.0,
   "points": 1,
   "series": {
    "2026-07-08": 8490
   }
  }
 }
}